mongo_adapter/__init__.py
mongo_adapter/__version__.py
mongo_adapter/adapter.py
mongo_adapter/client.py
mongo_adapter/exceptions.py
mongo_adapter-0.3.3.dist-info/LICENSE
mongo_adapter-0.3.3.dist-info/METADATA
mongo_adapter-0.3.3.dist-info/WHEEL
mongo_adapter-0.3.3.dist-info/top_level.txt
mongo_adapter-0.3.3.dist-info/RECORD
