Metadata-Version: 2.1
Name: mongo-adapter
Version: 0.3.3
Summary: A python interface to handle connection to a mongod instance
Home-page: https://github.com/moonso/mongo_adapter
Author: Måns Magnusson
Author-email: mans.magnusson@scilifelab.se
License: MIT
Platform: UNKNOWN
Classifier: License :: OSI Approved :: MIT License
Classifier: Programming Language :: Python
Classifier: Programming Language :: Python :: 2.6
Classifier: Programming Language :: Python :: 2.7
Classifier: Programming Language :: Python :: 3
Classifier: Programming Language :: Python :: 3.3
Classifier: Programming Language :: Python :: 3.4
Classifier: Programming Language :: Python :: 3.5
Classifier: Programming Language :: Python :: 3.6
Classifier: Programming Language :: Python :: Implementation :: CPython
Classifier: Programming Language :: Python :: Implementation :: PyPy
Requires-Dist: pymongo
Requires-Dist: pytest
Requires-Dist: mongomock
